{
  "generated_at": "28 Apr 2026 15:14",
  "pay_period": "20 Apr \u2013 26 Apr 2026",
  "locations": [
    {
      "org": "Diamond Barbers Pty Ltd",
      "short_name": "Darwin",
      "pay_period_start": "2026-04-20",
      "pay_period_end": "2026-04-26",
      "payment_date": "2026-04-27",
      "gross_wages": 42646.29,
      "tax": 8578.0,
      "net_pay": 29669.36,
      "super": 4398.93,
      "employee_count": 21,
      "employees": [
        {
          "name": "Abuel Basallo",
          "gross": 2472.75,
          "net": 1715.87,
          "tax": 507.0,
          "super": 249.88
        },
        {
          "name": "Ahmet Koysu",
          "gross": 1706.38,
          "net": 1208.39,
          "tax": 322.0,
          "super": 175.99
        },
        {
          "name": "Airol Basallo",
          "gross": 2633.29,
          "net": 1767.11,
          "tax": 596.0,
          "super": 270.18
        },
        {
          "name": "Anthony  Crispo",
          "gross": 2718.45,
          "net": 1818.67,
          "tax": 620.0,
          "super": 279.78
        },
        {
          "name": "Avinash Borade",
          "gross": 2155.03,
          "net": 1483.23,
          "tax": 443.0,
          "super": 228.8
        },
        {
          "name": "David Garcia",
          "gross": 1083.4,
          "net": 828.84,
          "tax": 148.0,
          "super": 106.56
        },
        {
          "name": "Jack Matthew",
          "gross": 3056.08,
          "net": 2022.1,
          "tax": 711.0,
          "super": 322.98
        },
        {
          "name": "Jairo Espinosa Mejia",
          "gross": 1907.08,
          "net": 1231.9,
          "tax": 477.0,
          "super": 198.18
        },
        {
          "name": "Jamaine McGee",
          "gross": 1165.99,
          "net": 881.23,
          "tax": 175.0,
          "super": 109.76
        },
        {
          "name": "JoJo Aligam",
          "gross": 1940.5,
          "net": 1353.67,
          "tax": 393.0,
          "super": 193.83
        },
        {
          "name": "John Zagorianos",
          "gross": 1797.32,
          "net": 1290.06,
          "tax": 323.0,
          "super": 184.26
        },
        {
          "name": "Krish Manocha",
          "gross": 1254.55,
          "net": 945.13,
          "tax": 175.0,
          "super": 134.42
        },
        {
          "name": "Laura Marshall",
          "gross": 1553.5,
          "net": 1119.0,
          "tax": 270.0,
          "super": 164.5
        },
        {
          "name": "Liem Nguyen",
          "gross": 2319.05,
          "net": 1572.87,
          "tax": 514.0,
          "super": 232.18
        },
        {
          "name": "Luca Marzocchi",
          "gross": 1880.64,
          "net": 1428.86,
          "tax": 252.0,
          "super": 199.78
        },
        {
          "name": "Marianne Escobar",
          "gross": 2353.44,
          "net": 1626.06,
          "tax": 495.0,
          "super": 232.38
        },
        {
          "name": "Nikolaos Diamantis",
          "gross": 1938.46,
          "net": 1353.77,
          "tax": 377.0,
          "super": 207.69
        },
        {
          "name": "Robert Jugan",
          "gross": 1809.11,
          "net": 1274.28,
          "tax": 341.0,
          "super": 193.83
        },
        {
          "name": "Tam Nguyen",
          "gross": 2023.06,
          "net": 1431.57,
          "tax": 382.0,
          "super": 209.49
        },
        {
          "name": "Vincenzo Vanzanella",
          "gross": 2501.91,
          "net": 1682.85,
          "tax": 551.0,
          "super": 268.06
        },
        {
          "name": "Wilfred Vidal",
          "gross": 2376.3,
          "net": 1633.9,
          "tax": 506.0,
          "super": 236.4
        }
      ]
    },
    {
      "org": "Virtual",
      "short_name": "Townsville",
      "pay_period_start": "2026-04-20",
      "pay_period_end": "2026-04-26",
      "payment_date": "2026-04-28",
      "gross_wages": 10843.81,
      "tax": 2182.0,
      "net_pay": 7511.2,
      "super": 1150.61,
      "employee_count": 6,
      "employees": [
        {
          "name": "Alfon Amora",
          "gross": 2133.56,
          "net": 1477.58,
          "tax": 429.0,
          "super": 226.98
        },
        {
          "name": "Bailey Wosomo",
          "gross": 379.14,
          "net": 274.79,
          "tax": 64.0,
          "super": 40.35
        },
        {
          "name": "Brazil Lamsen",
          "gross": 2442.88,
          "net": 1659.3,
          "tax": 523.0,
          "super": 260.58
        },
        {
          "name": "Dion Mataele",
          "gross": 1702.4,
          "net": 1210.0,
          "tax": 310.0,
          "super": 182.4
        },
        {
          "name": "Jack Bastock",
          "gross": 1978.57,
          "net": 1377.65,
          "tax": 390.0,
          "super": 210.92
        },
        {
          "name": "Nelson Diwa",
          "gross": 2207.26,
          "net": 1511.88,
          "tax": 466.0,
          "super": 229.38
        }
      ]
    },
    {
      "org": "DIAMOND BARBERS CAIRNS PTY LTD",
      "short_name": "Cairns",
      "pay_period_start": "2026-04-20",
      "pay_period_end": "2026-04-26",
      "payment_date": "2026-04-28",
      "gross_wages": 12733.24,
      "tax": 2035.0,
      "net_pay": 9387.16,
      "super": 1311.08,
      "employee_count": 9,
      "employees": [
        {
          "name": "Alex Khaq",
          "gross": 1924.81,
          "net": 1364.78,
          "tax": 366.0,
          "super": 194.03
        },
        {
          "name": "Andrea Palma",
          "gross": 1832.58,
          "net": 1322.15,
          "tax": 323.0,
          "super": 187.43
        },
        {
          "name": "Ashleigh Campbell",
          "gross": 605.01,
          "net": 517.27,
          "tax": 26.0,
          "super": 61.74
        },
        {
          "name": "Dipen Magar",
          "gross": 610.2,
          "net": 510.82,
          "tax": 34.0,
          "super": 65.38
        },
        {
          "name": "Ethan Byrne",
          "gross": 1802.64,
          "net": 1270.5,
          "tax": 339.0,
          "super": 193.14
        },
        {
          "name": "Jerry Guevarra",
          "gross": 2634.2,
          "net": 1774.84,
          "tax": 591.0,
          "super": 268.36
        },
        {
          "name": "Kyle Abe-Abe",
          "gross": 1081.21,
          "net": 866.07,
          "tax": 108.0,
          "super": 107.14
        },
        {
          "name": "Luca Perrone",
          "gross": 1719.55,
          "net": 1310.73,
          "tax": 231.0,
          "super": 177.82
        },
        {
          "name": "Michael Dobbs",
          "gross": 523.04,
          "net": 450.0,
          "tax": 17.0,
          "super": 56.04
        }
      ]
    }
  ],
  "totals": {
    "gross_wages": 66223.34,
    "tax": 12795.0,
    "net_pay": 46567.72,
    "super": 6860.62,
    "employee_count": 36
  }
}